{"_ts":[1486218088,1486246058],"_r":{"breakdown":{"html":{"bytes":[5091,5091],"requests":[3,3]},"js":{"bytes":[135707,135707],"requests":[1,1]},"css":{"bytes":[55501,55501],"requests":[2,2]},"image":{"bytes":[1514,1514],"requests":[2,2]},"flash":{"bytes":[0,0],"requests":[0,0]},"font":{"bytes":[19529,19530],"requests":[2,2]},"other":{"bytes":[0,0],"requests":[0,0]}},"date":[1486218088,1486246058],"domElements":[113,113],"domInteractive":[874.4,889.2],"firstPaint":[1126,1140],"fullyLoaded":[1381.2,1377],"id":["170204_N4_AMT","170204_5V_Y4X"],"loadTime":[1300,1300.8],"render":[1266,1321.8],"SpeedIndex":[1274,1327],"TTFB":[226.4,229.4],"videoFrames":[[{"_t":0,"_vc":0},{"_t":1300,"_vc":92},{"_t":1500,"_vc":100}],[{"_t":0,"_vc":0},{"_t":1400,"_vc":100}]],"visualComplete":[1381.4,1398.2]}}